belvys/__init__.py
belvys/_version.py
belvys/adjustment.py
belvys/api.py
belvys/common.py
belvys/docs/BelVis REST Schnittstelle V2.pdf
belvys/docs/BelVis-REST-API_V3_DE.pdf
belvys/example.py
belvys/example_api_basic.yaml
belvys/example_api_complex.yaml
belvys/example_structure_basic.yaml
belvys/example_structure_complex.yaml
belvys/structure.py
belvys/tenant.py
belvys-0.3.0.dist-info/LICENSE
belvys-0.3.0.dist-info/METADATA
belvys-0.3.0.dist-info/WHEEL
belvys-0.3.0.dist-info/RECORD
