Metadata-Version: 2.1
Name: belvys
Version: 0.3.0
Summary: Package to fetch data through the REST API of energy portfolio management software "Belvis".
License: BSD-3
Author: rwijtvliet
Author-email: rwijtvliet@gmail.com
Requires-Python: >=3.10,<4.0
Classifier: License :: Other/Proprietary License
Classifier: Programming Language :: Python :: 3
Classifier: Programming Language :: Python :: 3.10
Classifier: Programming Language :: Python :: 3.11
Classifier: Programming Language :: Python :: 3.12
Requires-Dist: numpy (>=1.25.2,<2.0.0)
Requires-Dist: portfolyo (>=0.6.0,<0.7.0)
Requires-Dist: pyyaml (>=6.0.1,<7.0.0)
Requires-Dist: requests (>=2.31.0,<3.0.0)
Requires-Dist: tqdm (>=4.66.1,<5.0.0)
